{
  "project_info": {
    "project_number": "73584146349",
    "firebase_url": "https://bisyorapp.firebaseio.com",
    "project_id": "bisyorapp",
    "storage_bucket": "bisyorapp.appspot.com"
  },
  "client": [
    {
      "client_info": {
        "mobilesdk_app_id": "1:73584146349:android:f33acb3705fc6b95b75324",
        "android_client_info": {
          "package_name": "com.shopapp.bisyor"
        }
      },
      "oauth_client": [
        {
          "client_id": "73584146349-o9ljl58r5kdo0svrgvi7qv3r0hg824sh.apps.googleusercontent.com",
          "client_type": 3
        }
      ],
      "api_key": [
        {
          "current_key": "AIzaSyAJ_4LU3CxkKqbzcnnUjYKjvjNeO77wl_U"
        }
      ],
      "services": {
        "appinvite_service": {
          "other_platform_oauth_client": [
            {
              "client_id": "73584146349-o9ljl58r5kdo0svrgvi7qv3r0hg824sh.apps.googleusercontent.com",
              "client_type": 3
            }
          ]
        }
      }
    }
  ],
  "configuration_version": "1"
}